[
  {
    "component_id": "alb-payments",
    "type": "alb",
    "region": "us-east-1",
    "availability_zones": ["us-east-1a", "us-east-1b"],
    "owner_team": "platform-network",
    "connected_services": ["payments-api"]
  },
  {
    "component_id": "sg-payments-db",
    "type": "security_group",
    "region": "us-east-1",
    "availability_zones": ["us-east-1a"],
    "owner_team": "platform-network",
    "connected_services": ["payments-api", "db-payments-primary"]
  },
  {
    "component_id": "rds-payments",
    "type": "postgres",
    "region": "us-east-1",
    "availability_zones": ["us-east-1a"],
    "owner_team": "platform-data",
    "connected_services": ["payments-api"]
  },
  {
    "component_id": "alb-checkout",
    "type": "alb",
    "region": "us-east-1",
    "availability_zones": ["us-east-1a", "us-east-1b"],
    "owner_team": "platform-network",
    "connected_services": ["checkout-api"]
  },
  {
    "component_id": "queue-billing",
    "type": "sqs",
    "region": "us-east-1",
    "availability_zones": ["us-east-1b"],
    "owner_team": "billing-platform",
    "connected_services": ["billing-worker"]
  }
]
